README.rst
setup.py
brainiak/__init__.py
brainiak/cloud/__init__.py
brainiak/cloud/client.py
brainiak/cloud/consumer.py
brainiak/cloud/driver.py
brainiak/cloud/launcher.py
brainiak/cloud/publisher.py
brainiak/cloud/server.py
brainiak/cloud/ui.py
brainiak/cloud/watcher.py
brainiak/cloud/experiments/Experiment.py
brainiak/cloud/experiments/FCMAExperiment.py
brainiak/cloud/experiments/SearchlightExperiment.py
brainiak/cloud/experiments/__init__.py
brainiak/cloud/matlab/__init__.py
brainiak/cloud/utils/Config.py
brainiak/cloud/utils/Logger.py
brainiak/cloud/utils/__init__.py
brainiak_cloud.egg-info/PKG-INFO
brainiak_cloud.egg-info/SOURCES.txt
brainiak_cloud.egg-info/dependency_links.txt
brainiak_cloud.egg-info/entry_points.txt
brainiak_cloud.egg-info/requires.txt
brainiak_cloud.egg-info/top_level.txt