Metadata-Version: 1.2
Name: brainiak-cloud
Version: 0.0.1
Summary: Brain Imaging Analysis Kit Cloud
Home-page: https://github.com/brainiak/brainiak-cloud
Author: Princeton Neuroscience Institute and Intel Corporation
Author-email: dsuo@princeton.edu
License: Apache 2
Keywords: neuroscience,algorithm,fMRI,distributed,scalable
Platform: UNKNOWN
Requires-Python: >=3.4
